CHANGELOG.md
LICENSE
MANIFEST.in
README.md
setup.py
instance_selector/__init__.py
instance_selector/apps.py
instance_selector/blocks.py
instance_selector/constants.py
instance_selector/edit_handlers.py
instance_selector/exceptions.py
instance_selector/registry.py
instance_selector/selectors.py
instance_selector/urls.py
instance_selector/views.py
instance_selector/wagtail_hooks.py
instance_selector/widgets.py
instance_selector/static/instance_selector/instance_selector.css
instance_selector/static/instance_selector/instance_selector_embed.js
instance_selector/static/instance_selector/instance_selector_telepath.js
instance_selector/static/instance_selector/instance_selector_widget.js
instance_selector/templates/instance_selector/instance_selector_embed.html
instance_selector/templates/instance_selector/instance_selector_widget.html
instance_selector/templates/instance_selector/instance_selector_widget_display.html
wagtail_new_instance_selector.egg-info/PKG-INFO
wagtail_new_instance_selector.egg-info/SOURCES.txt
wagtail_new_instance_selector.egg-info/dependency_links.txt
wagtail_new_instance_selector.egg-info/requires.txt
wagtail_new_instance_selector.egg-info/top_level.txt